super_session_keys/__init__.py
super_session_keys/data.py
super_session_keys/mapping.py
super_session_keys-1.1.3.dist-info/licenses/LICENSE
super_session_keys-1.1.3.dist-info/METADATA
super_session_keys-1.1.3.dist-info/WHEEL
super_session_keys-1.1.3.dist-info/top_level.txt
super_session_keys-1.1.3.dist-info/RECORD
